Workbook

Sheet Clients_Onboarding
A1: client_id | B1: company_name | C1: industry | D1: region | E1: company_size | F1: plan_type | G1: sales_rep | H1: csm_assigned | I1: contract_signed_date | J1: onboarding_start_date | K1: onboarding_complete_date | L1: days_to_onboard | M1: onboarding_status | N1: sla_met_14_days | O1: onboarding_csat | P1: contract_quarter | Q1: implementation_manager | R1: implementation_priority | S1: kickoff_date | T1: go_live_date | U1: delay_reason | V1: integration_required | W1: integration_type | X1: customer_segment | Y1: go_live_status | Z1: implementation_risk
A2: CB-1000 | B2: Vertex Solutions | C2: Manufacturing | D2: Chennai | E2: Small (1-50) | F2: Starter | G2: K. Joshi | H2: S. Reddy | I2: 46067 | J2: 46068 | K2: 46091 | L2: 23 | M2: Completed | N2: No | O2: 3 | P2: 2026-Q1 | Q2: Priya Nair | R2: Low | S2: 46068 | T2: 46091 | U2: Technical Issue | V2: Yes | W2: API | X2: Enterprise | Y2: Completed | Z2: Low
A3: CB-1001 | B3: Apex Group | C3: Retail & E-commerce | D3: Hyderabad | E3: Small (1-50) | F3: Starter | G3: A. Mehta | H3: J. Pillai | I3: 45876 | J3: 45878 | K3: 45900 | L3: 22 | M3: Completed | N3: No | O3: 4.1 | P3: 2025-Q3 | Q3: Priya Nair | R3: High | S3: 45878 | T3: 45900 | U3: Customer Delay | V3: No | W3: None | X3: Enterprise | Y3: Completed | Z3: Medium
A4: CB-1002 | B4: Harborlight Group | C4: Professional Services | D4: Ahmedabad | E4: Small (1-50) | F4: Enterprise | G4: S. Kapoor | H4: N. Verma | I4: 46109 | J4: 46110 | K4: 46151 | L4: 41 | M4: Completed | N4: No | O4: 4 | P4: 2026-Q1 | Q4: Karan Mehta | R4: High | S4: 46110 | T4: 46151 | U4: Technical Issue | V4: No | W4: None | X4: SMB | Y4: Completed | Z4: High
A5: CB-1003 | B5: Northbridge Industries | C5: Retail & E-commerce | D5: Mumbai | E5: Small (1-50) | F5: Growth | G5: S. Kapoor | H5: N. Verma | I5: 46028 | J5: 46031 | K5: 46057 | L5: 26 | M5: Completed | N5: No | O5: 2.8 | P5: 2026-Q1 | Q5: Priya Nair | R5: High | S5: 46031 | T5: 46057 | U5: Missing Documents | V5: Yes | W5: CRM | X5: Mid-Market | Y5: Completed | Z5: Low
A6: CB-1004 | B6: Driftwood Networks | C6: Real Estate | D6: Ahmedabad | E6: Large (251+) | F6: Enterprise | G6: P. Nair | H6: M. Khan | I6: 45562 | J6: 45564 | K6: 45585 | L6: 21 | M6: Completed | N6: No | O6: 3.9 | P6: 2024-Q3 | Q6: Priya Nair | R6: High | S6: 45564 | T6: 45585 | U6: Integration Delay | V6: No | W6: None | X6: Enterprise | Y6: Completed | Z6: Medium
A7: CB-1005 | B7: Granite Pvt Ltd | C7: FinTech | D7: Ahmedabad | E7: Mid (51-250) | F7: Growth | G7: K. Joshi | H7: M. Khan | I7: 46163 | J7: 46165 | K7: 46192 | L7: 27 | M7: Completed | N7: No | O7: 2.7 | P7: 2026-Q2 | Q7: Amit Singh | R7: Low | S7: 46165 | T7: 46192 | U7: Technical Issue | V7: Yes | W7: None | X7: Mid-Market | Y7: Completed | Z7: Medium
A8: CB-1006 | B8: Stratos Systems | C8: Logistics & Supply Chain | D8: Pune | E8: Small (1-50) | F8: Starter | G8: V. Shah | H8: T. D'Souza | I8: 46061 | J8: 46062 | K8: 46084 | L8: 22 | M8: Completed | N8: No | O8: 4.6 | P8: 2026-Q1 | Q8: Priya Nair | R8: High | S8: 46062 | T8: 46084 | U8: Resource Constraint | V8: Yes | W8: ERP | X8: Mid-Market | Y8: Completed | Z8: Low
A9: CB-1007 | B9: Highline Enterprises | C9: Hospitality | D9: Chennai | E9: Small (1-50) | F9: Starter | G9: S. Kapoor | H9: S. Reddy | I9: 46073 | J9: 46076 | K9: 46099 | L9: 23 | M9: Completed | N9: No | O9: 3.6 | P9: 2026-Q1 | Q9: Neha Patel | R9: Medium | S9: 46076 | T9: 46099 | U9: Scope Change | V9: No | W9: None | X9: Enterprise | Y9: Completed | Z9: Low
A10: CB-1008 | B10: Coral Enterprises | C10: Retail & E-commerce | D10: Bangalore | E10: Small (1-50) | F10: Growth | G10: P. Nair | H10: M. Khan | I10: 45607 | J10: 45610 | K10: 45626 | L10: 16 | M10: Completed | N10: No | O10: 5 | P10: 2024-Q4 | Q10: Neha Patel | R10: Low | S10: 45610 | T10: 45626 | U10: Missing Documents | V10: No | W10: None | X10: Mid-Market | Y10: Completed | Z10: High
A11: CB-1009 | B11: Meridian Group | C11: Retail & E-commerce | D11: Delhi NCR | E11: Large (251+) | F11: Starter | G11: K. Joshi | H11: N. Verma | I11: 45883 | J11: 45886 | K11: 45910 | L11: 24 | M11: Completed | N11: No | O11: 3.5 | P11: 2025-Q3 | Q11: Karan Mehta | R11: Low | S11: 45886 | T11: 45910 | U11: Customer Delay | V11: No | W11: None | X11: SMB | Y11: Completed | Z11: High
A12: CB-1010 | B12: Foxglove Ventures | C12: Retail & E-commerce | D12: Pune | E12: Small (1-50) | F12: Growth | G12: P. Nair | H12: M. Khan | I12: 45829 | J12: 45830 | K12: 45848 | L12: 18 | M12: Completed | N12: No | O12: 2.6 | P12: 2025-Q2 | Q12: Priya Nair | R12: High | S12: 45830 | T12: 45848 | U12: Resource Constraint | V12: Yes | W12: HRMS | X12: Mid-Market | Y12: Completed | Z12: Low
A13: CB-1011 | B13: Ironwood Enterprises | C13: FinTech | D13: Chennai | E13: Mid (51-250) | F13: Growth | G13: V. Shah | H13: T. D'Souza | I13: 46141 | J13: 46143 | K13: 46167 | L13: 24 | M13: Completed | N13: No | O13: 2.8 | P13: 2026-Q2 | Q13: Amit Singh | R13: Medium | S13: 46143 | T13: 46167 | U13: Technical Issue | V13: No | W13: None | X13: Enterprise | Y13: Completed | Z13: High
... A19: CB-1017 | B19: Brightline Enterprises | C19: Healthcare | D19: Chennai | E19: Large (251+) | F19: Starter | G19: K. Joshi | H19: N. Verma | I19: 45514 | J19: 45516 | K19: 45529 | L19: 13 | M19: Completed | N19: Yes | O19: 4.2 | P19: 2024-Q3 | Q19: Rahul Sharma | R19: Medium | S19: 45516 | T19: 45529 | U19: None | V19: Yes | W19: SSO | X19: SMB | Y19: Completed | Z19: Medium
A20: CB-1018 | B20: Driftwood Technologies | C20: Healthcare | D20: Pune | E20: Mid (51-250) | F20: Starter | G20: V. Shah | H20: N. Verma | I20: 46094 | J20: 46095 | M20: Dropped | P20: 2026-Q1 | Q20: Neha Patel | R20: Low | S20: 46095 | U20: Technical Issue | V20: Yes | W20: None | X20: Mid-Market | Y20: Dropped | Z20: Medium
A21: CB-1019 | B21: Trailmark Technologies | C21: Retail & E-commerce | D21: Pune | E21: Large (251+) | F21: Growth | G21: A. Mehta | H21: S. Reddy | I21: 45992 | J21: 45993 | M21: Dropped | P21: 2025-Q4 | Q21: Priya Nair | R21: Low | S21: 45993 | U21: Integration Delay | V21: Yes | W21: None | X21: Mid-Market | Y21: Dropped | Z21: Low
A22: CB-1020 | B22: Highline Networks | C22: Hospitality | D22: Ahmedabad | E22: Mid (51-250) | F22: Growth | G22: V. Shah | H22: S. Reddy | I22: 46059 | J22: 46060 | K22: 46085 | L22: 25 | M22: Completed | N22: No | O22: 4.6 | P22: 2026-Q1 | Q22: Rahul Sharma | R22: Low | S22: 46060 | T22: 46085 | U22: Scope Change | V22: No | W22: None | X22: Enterprise | Y22: Completed | Z22: Medium
A23: CB-1021 | B23: Brightline Group | C23: Logistics & Supply Chain | D23: Mumbai | E23: Mid (51-250) | F23: Starter | G23: K. Joshi | H23: N. Verma | I23: 45817 | J23: 45818 | K23: 45834 | L23: 16 | M23: Completed | N23: No | O23: 5 | P23: 2025-Q2 | Q23: Amit Singh | R23: Medium | S23: 45818 | T23: 45834 | U23: Customer Delay | V23: No | W23: None | X23: SMB | Y23: Completed | Z23: High
A24: CB-1022 | B24: Coral Enterprises | C24: FinTech | D24: Mumbai | E24: Small (1-50) | F24: Growth | G24: R. Iyer | H24: S. Reddy | I24: 46160 | J24: 46162 | K24: 46182 | L24: 20 | M24: Completed | N24: No | O24: 3.4 | P24: 2026-Q2 | Q24: Amit Singh | R24: High | S24: 46162 | T24: 46182 | U24: Integration Delay | V24: No | W24: None | X24: Enterprise | Y24: Completed | Z24: High
A25: CB-1023 | B25: Cobalt Pvt Ltd | C25: Hospitality | D25: Hyderabad | E25: Mid (51-250) | F25: Growth | G25: S. Kapoor | H25: S. Reddy | I25: 46125 | J25: 46127 | K25: 46155 | L25: 28 | M25: Completed | N25: No | O25: 3.5 | P25: 2026-Q2 | Q25: Karan Mehta | R25: Medium | S25: 46127 | T25: 46155 | U25: Technical Issue | V25: No | W25: None | X25: Enterprise | Y25: Completed | Z25: Medium
A26: CB-1024 | B26: Anchor Group | C26: FinTech | D26: Hyderabad | E26: Large (251+) | F26: Growth | G26: A. Mehta | H26: N. Verma | I26: 46070 | J26: 46073 | K26: 46097 | L26: 24 | M26: Completed | N26: No | O26: 5 | P26: 2026-Q1 | Q26: Karan Mehta | R26: Medium | S26: 46073 | T26: 46097 | U26: Technical Issue | V26: No | W26: None | X26: Mid-Market | Y26: Completed | Z26: High
A27: CB-1025 | B27: Anchor Ventures | C27: Manufacturing | D27: Ahmedabad | E27: Small (1-50) | F27: Starter | G27: R. Iyer | H27: M. Khan | I27: 45681 | J27: 45683 | K27: 45698 | L27: 15 | M27: Completed | N27: No | O27: 3.5 | P27: 2025-Q1 | Q27: Neha Patel | R27: Medium | S27: 45683 | T27: 45698 | U27: Resource Constraint | V27: No | W27: None | X27: Mid-Market | Y27: Completed | Z27: Low
A28: CB-1026 | B28: Driftwood Industries | C28: Hospitality | D28: Hyderabad | E28: Small (1-50) | F28: Starter | G28: R. Iyer | H28: J. Pillai | I28: 45894 | J28: 45895 | K28: 45920 | L28: 25 | M28: Completed | N28: No | O28: 4.1 | P28: 2025-Q3 | Q28: Karan Mehta | R28: Medium | S28: 45895 | T28: 45920 | U28: Integration Delay | V28: No | W28: None | X28: Enterprise | Y28: Completed | Z28: Low
A29: CB-1027 | B29: Lumen Group | C29: Professional Services | D29: Delhi NCR | E29: Mid (51-250) | F29: Growth | G29: P. Nair | H29: T. D'Souza | I29: 45476 | J29: 45479 | K29: 45498 | L29: 19 | M29: Completed | N29: No | O29: 4.1 | P29: 2024-Q3 | Q29: Priya Nair | R29: High | S29: 45479 | T29: 45498 | U29: Resource Constraint | V29: Yes | W29: CRM | X29: SMB | Y29: Completed | Z29: High
A30: CB-1028 | B30: Skyward Pvt Ltd | C30: Hospitality | D30: Delhi NCR | E30: Large (251+) | F30: Growth | G30: A. Mehta | H30: S. Reddy | I30: 45638 | J30: 45641 | K30: 45658 | L30: 17 | M30: Completed | N30: No | O30: 4.3 | P30: 2024-Q4 | Q30: Priya Nair | R30: High | S30: 45641 | T30: 45658 | U30: Technical Issue | V30: No | W30: None | X30: Mid-Market | Y30: Completed | Z30: Low
A31: CB-1029 | B31: Skyward Group | C31: Real Estate | D31: Bangalore | E31: Small (1-50) | F31: Starter | G31: S. Kapoor | H31: S. Reddy | I31: 46020 | J31: 46023 | K31: 46044 | L31: 21 | M31: Completed | N31: No | O31: 4.1 | P31: 2025-Q4 | Q31: Neha Patel | R31: High | S31: 46023 | T31: 46044 | U31: Technical Issue | V31: Yes | W31: HRMS | X31: Enterprise | Y31: Completed | Z31: High
A32: CB-1030 | B32: Crestline Solutions | C32: Professional Services | D32: Bangalore | E32: Small (1-50) | F32: Growth | G32: S. Kapoor | H32: S. Reddy | I32: 46053 | J32: 46055 | K32: 46075 | L32: 20 | M32: Completed | N32: No | O32: 3.4 | P32: 2026-Q1 | Q32: Priya Nair | R32: Medium | S32: 46055 | T32: 46075 | U32: Scope Change | V32: Yes | W32: CRM | X32: SMB | Y32: Completed | Z32: Low
A33: CB-1031 | B33: Quantix Enterprises | C33: Manufacturing | D33: Delhi NCR | E33: Large (251+) | F33: Enterprise | G33: S. Kapoor | H33: J. Pillai | I33: 46159 | J33: 46162 | K33: 46192 | L33: 30 | M33: Completed | N33: No | O33: 2.8 | P33: 2026-Q2 | Q33: Neha Patel | R33: Low | S33: 46162 | T33: 46192 | U33: Resource Constraint | V33: Yes | W33: CRM | X33: Enterprise | Y33: Completed | Z33: Low
... A42: CB-1040 | B42: Trailmark Ventures | C42: FinTech | D42: Chennai | E42: Large (251+) | F42: Enterprise | G42: S. Kapoor | H42: S. Reddy | I42: 45875 | J42: 45877 | K42: 45907 | L42: 30 | M42: Completed | N42: No | O42: 3.4 | P42: 2025-Q3 | Q42: Amit Singh | R42: High | S42: 45877 | T42: 45907 | U42: Integration Delay | V42: Yes | W42: SSO | X42: SMB | Y42: Completed | Z42: Low
A43: CB-1041 | B43: Westgate Ventures | C43: Logistics & Supply Chain | D43: Bangalore | E43: Mid (51-250) | F43: Enterprise | G43: K. Joshi | H43: S. Reddy | I43: 46096 | J43: 46099 | M43: Dropped | P43: 2026-Q1 | Q43: Priya Nair | R43: Medium | S43: 46099 | U43: Technical Issue | V43: No | W43: None | X43: Mid-Market | Y43: Dropped | Z43: Low
A44: CB-1042 | B44: Skyward Labs | C44: Hospitality | D44: Delhi NCR | E44: Large (251+) | F44: Enterprise | G44: R. Iyer | H44: S. Reddy | I44: 46030 | J44: 46031 | K44: 46064 | L44: 33 | M44: Completed | N44: No | O44: 3.4 | P44: 2026-Q1 | Q44: Neha Patel | R44: Medium | S44: 46031 | T44: 46064 | U44: Missing Documents | V44: Yes | W44: HRMS | X44: SMB | Y44: Completed | Z44: High
A45: CB-1043 | B45: Granite Group | C45: Real Estate | D45: Pune | E45: Small (1-50) | F45: Growth | G45: K. Joshi | H45: N. Verma | I45: 45784 | J45: 45786 | K45: 45808 | L45: 22 | M45: Completed | N45: No | O45: 4.1 | P45: 2025-Q2 | Q45: Amit Singh | R45: Medium | S45: 45786 | T45: 45808 | U45: Scope Change | V45: No | W45: None | X45: Enterprise | Y45: Completed | Z45: Medium
A46: CB-1044 | B46: Coral Labs | C46: Logistics & Supply Chain | D46: Chennai | E46: Large (251+) | F46: Enterprise | G46: S. Kapoor | H46: S. Reddy | I46: 46096 | J46: 46099 | K46: 46131 | L46: 32 | M46: Completed | N46: No | O46: 3.5 | P46: 2026-Q1 | Q46: Neha Patel | R46: Medium | S46: 46099 | T46: 46131 | U46: Integration Delay | V46: No | W46: None | X46: Mid-Market | Y46: Completed | Z46: High
A47: CB-1045 | B47: Northbridge Systems | C47: Retail & E-commerce | D47: Ahmedabad | E47: Small (1-50) | F47: Growth | G47: P. Nair | H47: M. Khan | I47: 46083 | J47: 46085 | K47: 46108 | L47: 23 | M47: Completed | N47: No | O47: 3.2 | P47: 2026-Q1 | Q47: Priya Nair | R47: High | S47: 46085 | T47: 46108 | U47: Resource Constraint | V47: No | W47: None | X47: Mid-Market | Y47: Completed | Z47: Medium
A48: CB-1046 | B48: Anchor Networks | C48: FinTech | D48: Bangalore | E48: Mid (51-250) | F48: Enterprise | G48: V. Shah | H48: J. Pillai | I48: 45841 | J48: 45842 | K48: 45869 | L48: 27 | M48: Completed | N48: No | O48: 3.2 | P48: 2025-Q3 | Q48: Priya Nair | R48: Low | S48: 45842 | T48: 45869 | U48: Customer Delay | V48: Yes | W48: ERP | X48: Mid-Market | Y48: Completed | Z48: High
A49: CB-1047 | B49: Apex Enterprises | C49: Retail & E-commerce | D49: Hyderabad | E49: Large (251+) | F49: Growth | G49: S. Kapoor | H49: J. Pillai | I49: 45765 | J49: 45768 | K49: 45789 | L49: 21 | M49: Completed | N49: No | O49: 3.9 | P49: 2025-Q2 | Q49: Rahul Sharma | R49: Medium | S49: 45768 | T49: 45789 | U49: Scope Change | V49: No | W49: None | X49: Mid-Market | Y49: Completed | Z49: High
A50: CB-1048 | B50: Brightline Group | C50: Manufacturing | D50: Ahmedabad | E50: Mid (51-250) | F50: Growth | G50: A. Mehta | H50: T. D'Souza | I50: 46020 | J50: 46021 | K50: 46043 | L50: 22 | M50: Completed | N50: No | O50: 4.9 | P50: 2025-Q4 | Q50: Rahul Sharma | R50: Medium | S50: 46021 | T50: 46043 | U50: Customer Delay | V50: Yes | W50: None | X50: SMB | Y50: Completed | Z50: Medium
A51: CB-1049 | B51: Crestline Technologies | C51: Retail & E-commerce | D51: Bangalore | E51: Small (1-50) | F51: Starter | G51: R. Iyer | H51: S. Reddy | I51: 45621 | J51: 45623 | K51: 45641 | L51: 18 | M51: Completed | N51: No | O51: 3 | P51: 2024-Q4 | Q51: Karan Mehta | R51: High | S51: 45623 | T51: 45641 | U51: Technical Issue | V51: Yes | W51: CRM | X51: SMB | Y51: Completed | Z51: High
A52: CB-1050 | B52: Cinder Labs | C52: FinTech | D52: Delhi NCR | E52: Large (251+) | F52: Starter | G52: S. Kapoor | H52: T. D'Souza | I52: 45686 | J52: 45689 | K52: 45699 | L52: 10 | M52: Completed | N52: Yes | O52: 2.5 | P52: 2025-Q1 | Q52: Amit Singh | R52: Low | S52: 45689 | T52: 45699 | U52: None | V52: No | W52: None | X52: SMB | Y52: Completed | Z52: Medium
A53: CB-1051 | B53: Foxglove Industries | C53: Logistics & Supply Chain | D53: Hyderabad | E53: Small (1-50) | F53: Starter | G53: P. Nair | H53: T. D'Souza | I53: 45367 | J53: 45368 | K53: 45378 | L53: 10 | M53: Completed | N53: Yes | O53: 4.4 | P53: 2024-Q1 | Q53: Karan Mehta | R53: Low | S53: 45368 | T53: 45378 | U53: None | V53: No | W53: None | X53: Enterprise | Y53: Completed | Z53: Low
A54: CB-1052 | B54: Nimbus Group | C54: Healthcare | D54: Chennai | E54: Mid (51-250) | F54: Growth | G54: K. Joshi | H54: J. Pillai | I54: 46074 | J54: 46076 | K54: 46105 | L54: 29 | M54: Completed | N54: No | O54: 3.5 | P54: 2026-Q1 | Q54: Karan Mehta | R54: High | S54: 46076 | T54: 46105 | U54: Integration Delay | V54: No | W54: None | X54: Enterprise | Y54: Completed | Z54: Medium
A55: CB-1053 | B55: Highline Industries | C55: Real Estate | D55: Delhi NCR | E55: Small (1-50) | F55: Growth | G55: R. Iyer | H55: J. Pillai | I55: 46011 | J55: 46013 | K55: 46035 | L55: 22 | M55: Completed | N55: No | O55: 3.7 | P55: 2025-Q4 | Q55: Neha Patel | R55: Medium | S55: 46013 | T55: 46035 | U55: Missing Documents | V55: Yes | W55: HRMS | X55: Mid-Market | Y55: Completed | Z55: Low
... A92: CB-1090 | B92: Quantix Systems | C92: Hospitality | D92: Delhi NCR | E92: Mid (51-250) | F92: Growth | G92: V. Shah | H92: S. Reddy | I92: 45636 | J92: 45637 | K92: 45657 | L92: 20 | M92: Completed | N92: No | O92: 3.8 | P92: 2024-Q4 | Q92: Karan Mehta | R92: Low | S92: 45637 | T92: 45657 | U92: Customer Delay | V92: No | W92: None | X92: SMB | Y92: Completed | Z92: Medium
A93: CB-1091 | B93: Trailmark Systems | C93: EdTech | D93: Pune | E93: Mid (51-250) | F93: Starter | G93: A. Mehta | H93: N. Verma | I93: 46027 | J93: 46029 | M93: Dropped | P93: 2026-Q1 | Q93: Priya Nair | R93: Medium | S93: 46029 | U93: Missing Documents | V93: Yes | W93: SSO | X93: Mid-Market | Y93: Dropped | Z93: Medium
A94: CB-1092 | B94: Larkspur Pvt Ltd | C94: Real Estate | D94: Pune | E94: Large (251+) | F94: Growth | G94: V. Shah | H94: T. D'Souza | I94: 45881 | J94: 45882 | K94: 45900 | L94: 18 | M94: Completed | N94: No | O94: 3.7 | P94: 2025-Q3 | Q94: Rahul Sharma | R94: Medium | S94: 45882 | T94: 45900 | U94: Scope Change | V94: No | W94: None | X94: SMB | Y94: Completed | Z94: Low
A95: CB-1093 | B95: Brightline Industries | C95: Healthcare | D95: Pune | E95: Mid (51-250) | F95: Enterprise | G95: V. Shah | H95: S. Reddy | I95: 45836 | J95: 45838 | K95: 45857 | L95: 19 | M95: Completed | N95: No | O95: 2.6 | P95: 2025-Q2 | Q95: Karan Mehta | R95: High | S95: 45838 | T95: 45857 | U95: Technical Issue | V95: No | W95: None | X95: Enterprise | Y95: Completed | Z95: High
A96: CB-1094 | B96: Coral Industries | C96: Healthcare | D96: Hyderabad | E96: Large (251+) | F96: Starter | G96: P. Nair | H96: T. D'Souza | I96: 45776 | J96: 45778 | K96: 45793 | L96: 15 | M96: Completed | N96: No | O96: 3.9 | P96: 2025-Q2 | Q96: Amit Singh | R96: Low | S96: 45778 | T96: 45793 | U96: Resource Constraint | V96: No | W96: None | X96: Mid-Market | Y96: Completed | Z96: Medium
A97: CB-1095 | B97: Veridian Ventures | C97: Logistics & Supply Chain | D97: Bangalore | E97: Large (251+) | F97: Enterprise | G97: S. Kapoor | H97: T. D'Souza | I97: 45992 | J97: 45993 | K97: 46026 | L97: 33 | M97: Completed | N97: No | O97: 3.9 | P97: 2025-Q4 | Q97: Karan Mehta | R97: Medium | S97: 45993 | T97: 46026 | U97: Scope Change | V97: Yes | W97: HRMS | X97: Enterprise | Y97: Completed | Z97: High
A98: CB-1096 | B98: Summit Pvt Ltd | C98: Real Estate | D98: Pune | E98: Large (251+) | F98: Enterprise | G98: R. Iyer | H98: S. Reddy | I98: 45822 | J98: 45823 | K98: 45851 | L98: 28 | M98: Completed | N98: No | O98: 4 | P98: 2025-Q2 | Q98: Priya Nair | R98: Medium | S98: 45823 | T98: 45851 | U98: Technical Issue | V98: Yes | W98: CRM | X98: SMB | Y98: Completed | Z98: Low
A99: CB-1097 | B99: Coral Solutions | C99: FinTech | D99: Hyderabad | E99: Mid (51-250) | F99: Starter | G99: S. Kapoor | H99: M. Khan | I99: 45553 | J99: 45554 | K99: 45567 | L99: 13 | M99: Completed | N99: Yes | O99: 4 | P99: 2024-Q3 | Q99: Neha Patel | R99: High | S99: 45554 | T99: 45567 | U99: None | V99: Yes | W99: HRMS | X99: Enterprise | Y99: Completed | Z99: Low
A100: CB-1098 | B100: Apex Industries | C100: Logistics & Supply Chain | D100: Chennai | E100: Mid (51-250) | F100: Enterprise | G100: S. Kapoor | H100: N. Verma | I100: 45594 | J100: 45596 | K100: 45615 | L100: 19 | M100: Completed | N100: No | O100: 4 | P100: 2024-Q4 | Q100: Amit Singh | R100: High | S100: 45596 | T100: 45615 | U100: Customer Delay | V100: Yes | W100: None | X100: Mid-Market | Y100: Completed | Z100: High
A101: CB-1099 | B101: Granite Enterprises | C101: Professional Services | D101: Hyderabad | E101: Large (251+) | F101: Starter | G101: A. Mehta | H101: T. D'Souza | I101: 46157 | J101: 46158 | K101: 46182 | L101: 24 | M101: Completed | N101: No | O101: 5 | P101: 2026-Q2 | Q101: Karan Mehta | R101: Medium | S101: 46158 | T101: 46182 | U101: Integration Delay | V101: No | W101: None | X101: Enterprise | Y101: Completed | Z101: Low
A102: CB-1100 | B102: Larkspur Ventures | C102: Healthcare | D102: Ahmedabad | E102: Small (1-50) | F102: Starter | G102: P. Nair | H102: M. Khan | I102: 46132 | J102: 46134 | K102: 46158 | L102: 24 | M102: Completed | N102: No | O102: 2.9 | P102: 2026-Q2 | Q102: Rahul Sharma | R102: Medium | S102: 46134 | T102: 46158 | U102: Integration Delay | V102: No | W102: None | X102: Enterprise | Y102: Completed | Z102: Low
A103: CB-1101 | B103: Larkspur Labs | C103: Real Estate | D103: Hyderabad | E103: Mid (51-250) | F103: Starter | G103: R. Iyer | H103: T. D'Souza | I103: 46029 | J103: 46031 | K103: 46056 | L103: 25 | M103: Completed | N103: No | O103: 3.4 | P103: 2026-Q1 | Q103: Rahul Sharma | R103: Low | S103: 46031 | T103: 46056 | U103: Technical Issue | V103: No | W103: None | X103: Mid-Market | Y103: Completed | Z103: Medium
A104: CB-1102 | B104: Veridian Ventures | C104: Retail & E-commerce | D104: Delhi NCR | E104: Mid (51-250) | F104: Starter | G104: A. Mehta | H104: S. Reddy | I104: 45746 | J104: 45747 | K104: 45767 | L104: 20 | M104: Completed | N104: No | O104: 4.4 | P104: 2025-Q1 | Q104: Neha Patel | R104: Low | S104: 45747 | T104: 45767 | U104: Customer Delay | V104: No | W104: None | X104: Enterprise | Y104: Completed | Z104: Low
A105: CB-1103 | B105: Pivotal Pvt Ltd | C105: Professional Services | D105: Chennai | E105: Large (251+) | F105: Growth | G105: S. Kapoor | H105: S. Reddy | I105: 46160 | J105: 46163 | K105: 46194 | L105: 31 | M105: Completed | N105: No | O105: 4.6 | P105: 2026-Q2 | Q105: Neha Patel | R105: High | S105: 46163 | T105: 46194 | U105: Integration Delay | V105: Yes | W105: SSO | X105: Mid-Market | Y105: Completed | Z105: Medium
... A111: CB-1109 | B111: Harborlight Solutions | C111: FinTech | D111: Ahmedabad | E111: Large (251+) | F111: Enterprise | G111: S. Kapoor | H111: S. Reddy | I111: 46129 | J111: 46132 | K111: 46159 | L111: 27 | M111: Completed | N111: No | O111: 3.5 | P111: 2026-Q2 | Q111: Amit Singh | R111: Medium | S111: 46132 | T111: 46159 | U111: Technical Issue | V111: No | W111: None | X111: Enterprise | Y111: Completed | Z111: Medium
A112: CB-1110 | B112: Cinder Industries | C112: Healthcare | D112: Chennai | E112: Mid (51-250) | F112: Growth | G112: S. Kapoor | H112: S. Reddy | I112: 45887 | J112: 45889 | M112: Dropped | P112: 2025-Q3 | Q112: Amit Singh | R112: Low | S112: 45889 | U112: Missing Documents | V112: Yes | W112: API | X112: Mid-Market | Y112: Dropped | Z112: Low
A113: CB-1111 | B113: Veridian Ventures | C113: Logistics & Supply Chain | D113: Bangalore | E113: Small (1-50) | F113: Starter | G113: S. Kapoor | H113: T. D'Souza | I113: 45688 | J113: 45691 | K113: 45701 | L113: 10 | M113: Completed | N113: Yes | O113: 4.1 | P113: 2025-Q1 | Q113: Neha Patel | R113: Medium | S113: 45691 | T113: 45701 | U113: None | V113: No | W113: None | X113: Mid-Market | Y113: Completed | Z113: High
A114: CB-1112 | B114: Coral Industries | C114: Manufacturing | D114: Delhi NCR | E114: Mid (51-250) | F114: Starter | G114: P. Nair | H114: M. Khan | I114: 45779 | J114: 45781 | K114: 45800 | L114: 19 | M114: Completed | N114: No | O114: 3.8 | P114: 2025-Q2 | Q114: Amit Singh | R114: Medium | S114: 45781 | T114: 45800 | U114: Technical Issue | V114: Yes | W114: SSO | X114: Enterprise | Y114: Completed | Z114: Medium
A115: CB-1113 | B115: Veridian Labs | C115: Logistics & Supply Chain | D115: Chennai | E115: Large (251+) | F115: Enterprise | G115: R. Iyer | H115: S. Reddy | I115: 45963 | J115: 45965 | M115: Dropped | P115: 2025-Q4 | Q115: Priya Nair | R115: High | S115: 45965 | U115: Technical Issue | V115: Yes | W115: None | X115: Mid-Market | Y115: Dropped | Z115: Low
A116: CB-1114 | B116: Vertex Industries | C116: FinTech | D116: Hyderabad | E116: Mid (51-250) | F116: Starter | G116: A. Mehta | H116: T. D'Souza | I116: 45662 | J116: 45664 | K116: 45676 | L116: 12 | M116: Completed | N116: Yes | O116: 4.3 | P116: 2025-Q1 | Q116: Neha Patel | R116: High | S116: 45664 | T116: 45676 | U116: None | V116: Yes | W116: HRMS | X116: Enterprise | Y116: Completed | Z116: High
A117: CB-1115 | B117: Lumen Technologies | C117: Manufacturing | D117: Hyderabad | E117: Small (1-50) | F117: Starter | G117: K. Joshi | H117: T. D'Souza | I117: 46108 | J117: 46109 | K117: 46139 | L117: 30 | M117: Completed | N117: No | O117: 4.3 | P117: 2026-Q1 | Q117: Rahul Sharma | R117: Low | S117: 46109 | T117: 46139 | U117: Scope Change | V117: Yes | W117: ERP | X117: SMB | Y117: Completed | Z117: Low
A118: CB-1116 | B118: Anchor Industries | C118: Real Estate | D118: Ahmedabad | E118: Mid (51-250) | F118: Enterprise | G118: V. Shah | H118: N. Verma | I118: 46060 | J118: 46062 | K118: 46086 | L118: 24 | M118: Completed | N118: No | O118: 4.6 | P118: 2026-Q1 | Q118: Amit Singh | R118: High | S118: 46062 | T118: 46086 | U118: Scope Change | V118: No | W118: None | X118: Mid-Market | Y118: Completed | Z118: Low
A119: CB-1117 | B119: Meridian Ventures | C119: Professional Services | D119: Mumbai | E119: Large (251+) | F119: Growth | G119: V. Shah | H119: J. Pillai | I119: 46040 | J119: 46041 | K119: 46068 | L119: 27 | M119: Completed | N119: No | O119: 3.5 | P119: 2026-Q1 | Q119: Priya Nair | R119: Medium | S119: 46041 | T119: 46068 | U119: Missing Documents | V119: Yes | W119: ERP | X119: Enterprise | Y119: Completed | Z119: Medium
A120: CB-1118 | B120: Orbit Group | C120: Hospitality | D120: Chennai | E120: Large (251+) | F120: Starter | G120: R. Iyer | H120: J. Pillai | I120: 45871 | J120: 45874 | K120: 45893 | L120: 19 | M120: Completed | N120: No | O120: 3.9 | P120: 2025-Q3 | Q120: Neha Patel | R120: Medium | S120: 45874 | T120: 45893 | U120: Scope Change | V120: No | W120: None | X120: SMB | Y120: Completed | Z120: Low
A121: CB-1119 | B121: Quantix Enterprises | C121: Healthcare | D121: Pune | E121: Mid (51-250) | F121: Starter | G121: R. Iyer | H121: N. Verma | I121: 45990 | J121: 45992 | K121: 46018 | L121: 26 | M121: Completed | N121: No | O121: 4.5 | P121: 2025-Q4 | Q121: Priya Nair | R121: Medium | S121: 45992 | T121: 46018 | U121: Scope Change | V121: No | W121: None | X121: SMB | Y121: Completed | Z121: High
A122: CB-1120 | B122: Summit Enterprises | C122: EdTech | D122: Ahmedabad | E122: Mid (51-250) | F122: Enterprise | G122: V. Shah | H122: T. D'Souza | I122: 45966 | J122: 45969 | K122: 46002 | L122: 33 | M122: Completed | N122: No | O122: 4 | P122: 2025-Q4 | Q122: Priya Nair | R122: Low | S122: 45969 | T122: 46002 | U122: Integration Delay | V122: No | W122: None | X122: Enterprise | Y122: Completed | Z122: Medium
A123: CB-1121 | B123: Beacon Pvt Ltd | C123: FinTech | D123: Bangalore | E123: Small (1-50) | F123: Starter | G123: R. Iyer | H123: J. Pillai | I123: 46003 | J123: 46004 | K123: 46023 | L123: 19 | M123: Completed | N123: No | O123: 3.9 | P123: 2025-Q4 | Q123: Priya Nair | R123: High | S123: 46004 | T123: 46023 | U123: Scope Change | V123: Yes | W123: API | X123: Mid-Market | Y123: Completed | Z123: Medium
A124: CB-1122 | B124: Driftwood Industries | C124: Real Estate | D124: Delhi NCR | E124: Mid (51-250) | F124: Growth | G124: P. Nair | H124: S. Reddy | I124: 45548 | J124: 45549 | K124: 45567 | L124: 18 | M124: Completed | N124: No | O124: 5 | P124: 2024-Q3 | Q124: Priya Nair | R124: Medium | S124: 45549 | T124: 45567 | U124: Technical Issue | V124: Yes | W124: API | X124: SMB | Y124: Completed | Z124: Medium
A125: CB-1123 | B125: Beacon Enterprises | C125: Hospitality | D125: Chennai | E125: Large (251+) | F125: Enterprise | G125: S. Kapoor | H125: S. Reddy | I125: 45860 | J125: 45861 | K125: 45887 | L125: 26 | M125: Completed | N125: No | O125: 4.1 | P125: 2025-Q3 | Q125: Karan Mehta | R125: Low | S125: 45861 | T125: 45887 | U125: Customer Delay | V125: No | W125: None | X125: Mid-Market | Y125: Completed | Z125: High
A126: CB-1124 | B126: Orbit Technologies | C126: EdTech | D126: Chennai | E126: Large (251+) | F126: Enterprise | G126: R. Iyer | H126: J. Pillai | I126: 45471 | J126: 45473 | K126: 45493 | L126: 20 | M126: Completed | N126: No | O126: 4.1 | P126: 2024-Q2 | Q126: Priya Nair | R126: Medium | S126: 45473 | T126: 45493 | U126: Customer Delay | V126: No | W126: None | X126: Mid-Market | Y126: Completed | Z126: High
A127: CB-1125 | B127: Granite Ventures | C127: EdTech | D127: Chennai | E127: Small (1-50) | F127: Starter | G127: P. Nair | H127: J. Pillai | I127: 45911 | J127: 45914 | K127: 45925 | L127: 11 | M127: Completed | N127: Yes | O127: 4.4 | P127: 2025-Q3 | Q127: Rahul Sharma | R127: Low | S127: 45914 | T127: 45925 | U127: None | V127: Yes | W127: None | X127: Enterprise | Y127: Completed | Z127: High
... A133: CB-1131 | B133: Orbit Networks | C133: Logistics & Supply Chain | D133: Bangalore | E133: Small (1-50) | F133: Starter | G133: S. Kapoor | H133: T. D'Souza | I133: 46140 | J133: 46142 | K133: 46162 | L133: 20 | M133: Completed | N133: No | O133: 3.9 | P133: 2026-Q2 | Q133: Priya Nair | R133: High | S133: 46142 | T133: 46162 | U133: Customer Delay | V133: Yes | W133: ERP | X133: SMB | Y133: Completed | Z133: Low
A134: CB-1132 | B134: Lumen Labs | C134: FinTech | D134: Bangalore | E134: Small (1-50) | F134: Enterprise | G134: R. Iyer | H134: S. Reddy | I134: 45964 | J134: 45967 | M134: Dropped | P134: 2025-Q4 | Q134: Priya Nair | R134: Medium | S134: 45967 | U134: Customer Delay | V134: No | W134: None | X134: Enterprise | Y134: Dropped | Z134: Low
A135: CB-1133 | B135: Brightline Technologies | C135: Real Estate | D135: Ahmedabad | E135: Large (251+) | F135: Growth | G135: A. Mehta | H135: S. Reddy | I135: 45811 | J135: 45813 | K135: 45832 | L135: 19 | M135: Completed | N135: No | O135: 4.5 | P135: 2025-Q2 | Q135: Priya Nair | R135: High | S135: 45813 | T135: 45832 | U135: Technical Issue | V135: Yes | W135: SSO | X135: Mid-Market | Y135: Completed | Z135: Medium
A136: CB-1134 | B136: Cobalt Ventures | C136: Healthcare | D136: Bangalore | E136: Small (1-50) | F136: Starter | G136: R. Iyer | H136: S. Reddy | I136: 45970 | J136: 45973 | K136: 45998 | L136: 25 | M136: Completed | N136: No | O136: 2.9 | P136: 2025-Q4 | Q136: Karan Mehta | R136: Low | S136: 45973 | T136: 45998 | U136: Missing Documents | V136: Yes | W136: API | X136: Enterprise | Y136: Completed | Z136: High
A137: CB-1135 | B137: Larkspur Solutions | C137: Hospitality | D137: Hyderabad | E137: Mid (51-250) | F137: Enterprise | G137: K. Joshi | H137: S. Reddy | I137: 45425 | J137: 45428 | K137: 45450 | L137: 22 | M137: Completed | N137: No | O137: 4.3 | P137: 2024-Q2 | Q137: Amit Singh | R137: Medium | S137: 45428 | T137: 45450 | U137: Resource Constraint | V137: No | W137: None | X137: SMB | Y137: Completed | Z137: Low
A138: CB-1136 | B138: Lumen Ventures | C138: EdTech | D138: Hyderabad | E138: Mid (51-250) | F138: Growth | G138: K. Joshi | H138: T. D'Souza | I138: 46155 | J138: 46156 | K138: 46176 | L138: 20 | M138: Completed | N138: No | O138: 3.1 | P138: 2026-Q2 | Q138: Karan Mehta | R138: Low | S138: 46156 | T138: 46176 | U138: Missing Documents | V138: No | W138: None | X138: Mid-Market | Y138: Completed | Z138: High
A139: CB-1137 | B139: Quantix Group | C139: Real Estate | D139: Chennai | E139: Large (251+) | F139: Enterprise | G139: S. Kapoor | H139: N. Verma | I139: 45904 | J139: 45905 | K139: 45934 | L139: 29 | M139: Completed | N139: No | O139: 5 | P139: 2025-Q3 | Q139: Rahul Sharma | R139: High | S139: 45905 | T139: 45934 | U139: Missing Documents | V139: Yes | W139: None | X139: SMB | Y139: Completed | Z139: High
A140: CB-1138 | B140: Summit Industries | C140: EdTech | D140: Delhi NCR | E140: Large (251+) | F140: Enterprise | G140: A. Mehta | H140: T. D'Souza | I140: 46072 | J140: 46074 | K140: 46104 | L140: 30 | M140: Completed | N140: No | O140: 3.5 | P140: 2026-Q1 | Q140: Rahul Sharma | R140: High | S140: 46074 | T140: 46104 | U140: Technical Issue | V140: Yes | W140: CRM | X140: SMB | Y140: Completed | Z140: Low
A141: CB-1139 | B141: Stratos Solutions | C141: Logistics & Supply Chain | D141: Bangalore | E141: Mid (51-250) | F141: Growth | G141: K. Joshi | H141: M. Khan | I141: 45545 | J141: 45546 | K141: 45560 | L141: 14 | M141: Completed | N141: Yes | O141: 3.2 | P141: 2024-Q3 | Q141: Rahul Sharma | R141: Low | S141: 45546 | T141: 45560 | U141: None | V141: Yes | W141: CRM | X141: Mid-Market | Y141: Completed | Z141: Low
A142: CB-1140 | B142: Meridian Ventures | C142: Manufacturing | D142: Bangalore | E142: Small (1-50) | F142: Starter | G142: S. Kapoor | H142: J. Pillai | I142: 45907 | J142: 45910 | K142: 45932 | L142: 22 | M142: Completed | N142: No | O142: 3.8 | P142: 2025-Q3 | Q142: Priya Nair | R142: High | S142: 45910 | T142: 45932 | U142: Integration Delay | V142: Yes | W142: ERP | X142: SMB | Y142: Completed | Z142: Low
A143: CB-1141 | B143: Quantix Systems | C143: Manufacturing | D143: Hyderabad | E143: Mid (51-250) | F143: Growth | G143: R. Iyer | H143: N. Verma | I143: 45909 | J143: 45911 | K143: 45936 | L143: 25 | M143: Completed | N143: No | O143: 4.3 | P143: 2025-Q3 | Q143: Priya Nair | R143: Low | S143: 45911 | T143: 45936 | U143: Integration Delay | V143: No | W143: None | X143: Mid-Market | Y143: Completed | Z143: High
A144: CB-1142 | B144: Westgate Ventures | C144: Professional Services | D144: Pune | E144: Small (1-50) | F144: Starter | G144: P. Nair | H144: J. Pillai | I144: 46146 | J144: 46149 | K144: 46172 | L144: 23 | M144: Completed | N144: No | O144: 3 | P144: 2026-Q2 | Q144: Amit Singh | R144: Low | S144: 46149 | T144: 46172 | U144: Technical Issue | V144: No | W144: None | X144: Enterprise | Y144: Completed | Z144: Medium
A145: CB-1143 | B145: Pivotal Group | C145: FinTech | D145: Ahmedabad | E145: Mid (51-250) | F145: Starter | G145: S. Kapoor | H145: T. D'Souza | I145: 45958 | J145: 45959 | M145: Dropped | P145: 2025-Q4 | Q145: Amit Singh | R145: High | S145: 45959 | U145: Integration Delay | V145: No | W145: None | X145: Mid-Market | Y145: Dropped | Z145: Low
A146: CB-1144 | B146: Beacon Ventures | C146: Retail & E-commerce | D146: Delhi NCR | E146: Large (251+) | F146: Enterprise | G146: V. Shah | H146: N. Verma | I146: 45898 | J146: 45901 | K146: 45930 | L146: 29 | M146: Completed | N146: No | O146: 4.8 | P146: 2025-Q3 | Q146: Rahul Sharma | R146: High | S146: 45901 | T146: 45930 | U146: Scope Change | V146: No | W146: None | X146: SMB | Y146: Completed | Z146: High
A147: CB-1145 | B147: Trailmark Systems | C147: Logistics & Supply Chain | D147: Pune | E147: Mid (51-250) | F147: Growth | G147: K. Joshi | H147: J. Pillai | I147: 45747 | J147: 45749 | K147: 45771 | L147: 22 | M147: Completed | N147: No | O147: 3.5 | P147: 2025-Q1 | Q147: Rahul Sharma | R147: Medium | S147: 45749 | T147: 45771 | U147: Resource Constraint | V147: No | W147: None | X147: Enterprise | Y147: Completed | Z147: Medium
A148: CB-1146 | B148: Beacon Systems | C148: Logistics & Supply Chain | D148: Chennai | E148: Mid (51-250) | F148: Growth | G148: S. Kapoor | H148: J. Pillai | I148: 45799 | J148: 45801 | K148: 45816 | L148: 15 | M148: Completed | N148: No | O148: 4.6 | P148: 2025-Q2 | Q148: Karan Mehta | R148: Low | S148: 45801 | T148: 45816 | U148: Customer Delay | V148: No | W148: None | X148: SMB | Y148: Completed | Z148: High
A149: CB-1147 | B149: Coral Pvt Ltd | C149: Logistics & Supply Chain | D149: Mumbai | E149: Mid (51-250) | F149: Enterprise | G149: V. Shah | H149: J. Pillai | I149: 45928 | J149: 45929 | K149: 45952 | L149: 23 | M149: Completed | N149: No | O149: 4.9 | P149: 2025-Q3 | Q149: Neha Patel | R149: Medium | S149: 45929 | T149: 45952 | U149: Missing Documents | V149: Yes | W149: API | X149: Enterprise | Y149: Completed | Z149: Medium
A150: CB-1148 | B150: Quantix Industries | C150: Healthcare | D150: Delhi NCR | E150: Large (251+) | F150: Enterprise | G150: R. Iyer | H150: M. Khan | I150: 45876 | J150: 45879 | K150: 45904 | L150: 25 | M150: Completed | N150: No | O150: 4.1 | P150: 2025-Q3 | Q150: Amit Singh | R150: High | S150: 45879 | T150: 45904 | U150: Technical Issue | V150: No | W150: None | X150: Enterprise | Y150: Completed | Z150: High
A151: CB-1149 | B151: Vertex Pvt Ltd | C151: Healthcare | D151: Pune | E151: Mid (51-250) | F151: Starter | G151: R. Iyer | H151: S. Reddy | I151: 45421 | J151: 45424 | K151: 45433 | L151: 9 | M151: Completed | N151: Yes | O151: 4.3 | P151: 2024-Q2 | Q151: Karan Mehta | R151: Medium | S151: 45424 | T151: 45433 | U151: None | V151: No | W151: None | X151: SMB | Y151: Completed | Z151: Medium
A152: CB-1150 | B152: Beacon Labs | C152: Retail & E-commerce | D152: Chennai | E152: Mid (51-250) | F152: Starter | G152: R. Iyer | H152: T. D'Souza | I152: 46093 | J152: 46094 | K152: 46120 | L152: 26 | M152: Completed | N152: No | O152: 4.1 | P152: 2026-Q1 | Q152: Karan Mehta | R152: Medium | S152: 46094 | T152: 46120 | U152: Resource Constraint | V152: Yes | W152: None | X152: SMB | Y152: Completed | Z152: Low
A153: CB-1151 | B153: Cobalt Labs | C153: Healthcare | D153: Ahmedabad | E153: Small (1-50) | F153: Starter | G153: V. Shah | H153: T. D'Souza | I153: 46126 | J153: 46127 | K153: 46152 | L153: 25 | M153: Completed | N153: No | O153: 2.6 | P153: 2026-Q2 | Q153: Amit Singh | R153: Medium | S153: 46127 | T153: 46152 | U153: Missing Documents | V153: No | W153: None | X153: Enterprise | Y153: Completed | Z153: High
A154: CB-1152 | B154: Foxglove Industries | C154: FinTech | D154: Chennai | E154: Large (251+) | F154: Enterprise | G154: P. Nair | H154: M. Khan | I154: 45622 | J154: 45624 | K154: 45640 | L154: 16 | M154: Completed | N154: No | O154: 3.9 | P154: 2024-Q4 | Q154: Neha Patel | R154: High | S154: 45624 | T154: 45640 | U154: Integration Delay | V154: Yes | W154: HRMS | X154: Mid-Market | Y154: Completed | Z154: Low
A155: CB-1153 | B155: Harborlight Networks | C155: Hospitality | D155: Delhi NCR | E155: Small (1-50) | F155: Growth | G155: V. Shah | H155: M. Khan | I155: 45948 | J155: 45949 | K155: 45965 | L155: 16 | M155: Completed | N155: No | O155: 4.2 | P155: 2025-Q4 | Q155: Rahul Sharma | R155: High | S155: 45949 | T155: 45965 | U155: Technical Issue | V155: No | W155: None | X155: SMB | Y155: Completed | Z155: Medium
A156: CB-1154 | B156: Pivotal Group | C156: Professional Services | D156: Delhi NCR | E156: Small (1-50) | F156: Growth | G156: V. Shah | H156: T. D'Souza | I156: 45582 | J156: 45583 | K156: 45602 | L156: 19 | M156: Completed | N156: No | O156: 5 | P156: 2024-Q4 | Q156: Karan Mehta | R156: Low | S156: 45583 | T156: 45602 | U156: Missing Documents | V156: No | W156: None | X156: Mid-Market | Y156: Completed | Z156: Low
A157: CB-1155 | B157: Driftwood Solutions | C157: Hospitality | D157: Pune | E157: Small (1-50) | F157: Starter | G157: R. Iyer | H157: S. Reddy | I157: 46015 | J157: 46017 | K157: 46036 | L157: 19 | M157: Completed | N157: No | O157: 3.4 | P157: 2025-Q4 | Q157: Priya Nair | R157: Medium | S157: 46017 | T157: 46036 | U157: Resource Constraint | V157: Yes | W157: ERP | X157: Enterprise | Y157: Completed | Z157: Medium
... A173: CB-1171 | B173: Larkspur Industries | C173: EdTech | D173: Pune | E173: Large (251+) | F173: Growth | G173: P. Nair | H173: S. Reddy | I173: 45924 | J173: 45925 | K173: 45941 | L173: 16 | M173: Completed | N173: No | O173: 3.6 | P173: 2025-Q3 | Q173: Karan Mehta | R173: High | S173: 45925 | T173: 45941 | U173: Technical Issue | V173: No | W173: None | X173: Mid-Market | Y173: Completed | Z173: High
A174: CB-1172 | B174: Meridian Systems | C174: FinTech | D174: Mumbai | E174: Mid (51-250) | F174: Starter | G174: V. Shah | H174: N. Verma | I174: 45738 | J174: 45740 | M174: Dropped | P174: 2025-Q1 | Q174: Neha Patel | R174: Low | S174: 45740 | U174: Customer Delay | V174: Yes | W174: ERP | X174: Enterprise | Y174: Dropped | Z174: Low
...

Sheet Renewals_HealthScore
A1: client_id | B1: plan_type | C1: annual_recurring_revenue_inr | D1: renewal_date | E1: usage_score | F1: support_tickets_90d | G1: payment_delay_days | H1: health_score | I1: renewal_outcome | J1: churn_reason | K1: renewed_arr_inr | L1: renewal_quarter
A2: CB-1004 | B2: Enterprise | C2: 492892 | D2: 45927 | E2: 55.3 | F2: 5 | G2: 0 | H2: 46.4 | I2: Renewed | K2: 498024 | L2: 2025-Q3
A3: CB-1008 | B3: Growth | C3: 148960 | D3: 45972 | E3: 91.3 | F3: 1 | G3: 2 | H3: 72.2 | I3: Renewed | K3: 145812 | L3: 2025-Q4
A4: CB-1010 | B4: Growth | C4: 148520 | D4: 46194 | E4: 46.7 | F4: 2 | G4: 2 | H4: 45.9 | I4: Churned | J4: Price increase at renewal | L4: 2026-Q2
A5: CB-1015 | B5: Starter | C5: 68846 | D5: 46077 | E5: 78.3 | F5: 2 | G5: 10 | H5: 58.5 | I5: Churned | J5: Company downsized or shut down | L5: 2026-Q1
A6: CB-1017 | B6: Starter | C6: 53470 | D6: 45879 | E6: 65.6 | F6: 2 | G6: 5 | H6: 54.5 | I6: Renewed | K6: 52377 | L6: 2025-Q3
A7: CB-1021 | B7: Starter | C7: 55243 | D7: 46182 | E7: 46.4 | F7: 2 | G7: 1 | H7: 46.3 | I7: Renewed - Upsold | K7: 68064 | L7: 2026-Q2
A8: CB-1025 | B8: Starter | C8: 56975 | D8: 46046 | E8: 78.6 | F8: 6 | G8: 13 | H8: 49.7 | I8: Renewed | K8: 59633 | L8: 2026-Q1
A9: CB-1027 | B9: Growth | C9: 224639 | D9: 45841 | E9: 54.9 | F9: 2 | G9: 1 | H9: 51 | I9: Renewed | K9: 222389 | L9: 2025-Q3
A10: CB-1028 | B10: Growth | C10: 176044 | D10: 46003 | E10: 70.9 | F10: 3 | G10: 2 | H10: 57.4 | I10: Renewed | K10: 184143 | L10: 2025-Q4
A11: CB-1032 | B11: Starter | C11: 73151 | D11: 46160 | E11: 58.9 | F11: 1 | G11: 2 | H11: 54.4 | I11: Renewed - Upsold | K11: 92401 | L11: 2026-Q2
A12: CB-1033 | B12: Enterprise | C12: 562250 | D12: 46193 | E12: 77.3 | F12: 3 | G12: 0 | H12: 62.1 | I12: Renewed | K12: 570463 | L12: 2026-Q2
A13: CB-1035 | B13: Starter | C13: 80445 | D13: 46040 | E13: 69.5 | F13: 5 | G13: 1 | H13: 53.6 | I13: Renewed | K13: 79284 | L13: 2026-Q1
A14: CB-1036 | B14: Starter | C14: 61572 | D14: 45974 | E14: 69.9 | F14: 2 | G14: 2 | H14: 58.6 | I14: Renewed | K14: 62939 | L14: 2025-Q4
A15: CB-1038 | B15: Starter | C15: 56538 | D15: 46077 | E15: 84.5 | F15: 2 | G15: 6 | H15: 64.3 | I15: Churned | J15: Poor onboarding experience | L15: 2026-Q1
A16: CB-1043 | B16: Growth | C16: 125597 | D16: 46149 | E16: 71 | F16: 2 | G16: 8 | H16: 55.7 | I16: Renewed | K16: 130738 | L16: 2026-Q2
A17: CB-1047 | B17: Growth | C17: 191630 | D17: 46130 | E17: 57.7 | F17: 4 | G17: 10 | H17: 43.5 | I17: At Risk - Pending Decision | L17: 2026-Q2
A18: CB-1049 | B18: Starter | C18: 66911 | D18: 45986 | E18: 67.4 | F18: 5 | G18: 3 | H18: 51.2 | I18: Renewed | K18: 67562 | L18: 2025-Q4
A19: CB-1050 | B19: Starter | C19: 59061 | D19: 46051 | E19: 74.2 | F19: 4 | G19: 4 | H19: 56.2 | I19: Renewed | K19: 60005 | L19: 2026-Q1
A20: CB-1051 | B20: Starter | C20: 73369 | D20: 45732 | E20: 77.5 | F20: 7 | G20: 9 | H20: 49.6 | I20: Renewed | K20: 73483 | L20: 2025-Q1
A21: CB-1058 | B21: Starter | C21: 72733 | D21: 45986 | E21: 49 | F21: 1 | G21: 1 | H21: 49.6 | I21: Renewed | K21: 73411 | L21: 2025-Q4
A22: CB-1059 | B22: Starter | C22: 39946 | D22: 45955 | E22: 56.2 | F22: 3 | G22: 0 | H22: 50.5 | I22: Renewed | K22: 40608 | L22: 2025-Q4
A23: CB-1067 | B23: Growth | C23: 227505 | D23: 46143 | E23: 65.4 | F23: 6 | G23: 1 | H23: 49.6 | I23: Renewed | K23: 232900 | L23: 2026-Q2
A24: CB-1068 | B24: Starter | C24: 67174 | D24: 45811 | E24: 71.5 | F24: 6 | G24: 3 | H24: 51.7 | I24: Renewed | K24: 68860 | L24: 2025-Q2
A25: CB-1070 | B25: Growth | C25: 145741 | D25: 46065 | E25: 66.1 | F25: 6 | G25: 3 | H25: 48.7 | I25: Churned | J25: Poor onboarding experience | L25: 2026-Q1
A26: CB-1073 | B26: Starter | C26: 49110 | D26: 46083 | E26: 45.3 | F26: 4 | G26: 3 | H26: 40.9 | I26: Renewed | K26: 49249 | L26: 2026-Q1
A27: CB-1074 | B27: Growth | C27: 226526 | D27: 45869 | E27: 62.6 | F27: 4 | G27: 0 | H27: 52.2 | I27: Renewed | K27: 224660 | L27: 2025-Q3
A28: CB-1075 | B28: Growth | C28: 219945 | D28: 46124 | E28: 77.8 | F28: 3 | G28: 0 | H28: 62.4 | I28: At Risk - Pending Decision | L28: 2026-Q2
A29: CB-1076 | B29: Enterprise | C29: 360933 | D29: 46134 | E29: 58.9 | F29: 3 | G29: 1 | H29: 51.4 | I29: Renewed | K29: 374285 | L29: 2026-Q2
A30: CB-1083 | B30: Starter | C30: 62277 | D30: 46017 | E30: 57 | F30: 8 | G30: 6 | H30: 38.4 | I30: Renewed | K30: 63774 | L30: 2025-Q4
A31: CB-1084 | B31: Enterprise | C31: 556688 | D31: 45789 | E31: 76.8 | F31: 4 | G31: 2 | H31: 58.8 | I31: Renewed | K31: 551555 | L31: 2025-Q2
A32: CB-1085 | B32: Growth | C32: 185821 | D32: 45921 | E32: 70 | F32: 1 | G32: 2 | H32: 60.5 | I32: Renewed - Upsold | K32: 235147 | L32: 2025-Q3
A33: CB-1088 | B33: Starter | C33: 55007 | D33: 46011 | E33: 66.3 | F33: 3 | G33: 12 | H33: 48.8 | I33: Churned | J33: Lack of key feature (AI/automation) | L33: 2025-Q4
A34: CB-1090 | B34: Growth | C34: 213032 | D34: 46001 | E34: 63.9 | F34: 5 | G34: 4 | H34: 48.7 | I34: Renewed | K34: 219100 | L34: 2025-Q4
A35: CB-1093 | B35: Enterprise | C35: 561274 | D35: 46201 | E35: 78.1 | F35: 1 | G35: 0 | H35: 66.1 | I35: Renewed | K35: 571230 | L35: 2026-Q2
A36: CB-1094 | B36: Starter | C36: 54238 | D36: 46141 | E36: 56.3 | F36: 3 | G36: 8 | H36: 45.8 | I36: Churned | J36: Lack of key feature (AI/automation) | L36: 2026-Q2
A37: CB-1096 | B37: Enterprise | C37: 533787 | D37: 46187 | E37: 64.5 | F37: 5 | G37: 1 | H37: 50.9 | I37: Renewed | K37: 529324 | L37: 2026-Q2
A38: CB-1097 | B38: Starter | C38: 76249 | D38: 45918 | E38: 100 | F38: 0 | G38: 14 | H38: 71.6 | I38: Renewed | K38: 75239 | L38: 2025-Q3
A39: CB-1098 | B39: Enterprise | C39: 492907 | D39: 45959 | E39: 71.5 | F39: 1 | G39: 8 | H39: 57.7 | I39: Renewed | K39: 510259 | L39: 2025-Q4
A40: CB-1102 | B40: Starter | C40: 70474 | D40: 46111 | E40: 82 | F40: 7 | G40: 0 | H40: 57.5 | I40: Renewed | K40: 70674 | L40: 2026-Q1
A41: CB-1107 | B41: Growth | C41: 135416 | D41: 46117 | E41: 60.2 | F41: 1 | G41: 2 | H41: 55.1 | I41: Renewed - Upsold | K41: 154176 | L41: 2026-Q2
A42: CB-1108 | B42: Starter | C42: 68131 | D42: 45930 | E42: 67.6 | F42: 2 | G42: 3 | H42: 56.8 | I42: Renewed | K42: 69076 | L42: 2025-Q3
A43: CB-1111 | B43: Starter | C43: 58744 | D43: 46053 | E43: 53.5 | F43: 0 | G43: 6 | H43: 50.8 | I43: Renewed - Upsold | K43: 79008 | L43: 2026-Q1
A44: CB-1112 | B44: Starter | C44: 65987 | D44: 46144 | E44: 88.6 | F44: 4 | G44: 5 | H44: 63.5 | I44: Renewed | K44: 64795 | L44: 2026-Q2
A45: CB-1114 | B45: Starter | C45: 53869 | D45: 46027 | E45: 86.4 | F45: 3 | G45: 12 | H45: 59.9 | I45: Renewed | K45: 54551 | L45: 2026-Q1
A46: CB-1122 | B46: Growth | C46: 231042 | D46: 45913 | E46: 76.2 | F46: 2 | G46: 3 | H46: 61.5 | I46: Renewed | K46: 224249 | L46: 2025-Q3
A47: CB-1124 | B47: Enterprise | C47: 425519 | D47: 45836 | E47: 65.7 | F47: 3 | G47: 5 | H47: 52.7 | I47: Renewed | K47: 419822 | L47: 2025-Q2
A48: CB-1126 | B48: Starter | C48: 45720 | D48: 46163 | E48: 90.4 | F48: 4 | G48: 0 | H48: 67.5 | I48: Renewed | K48: 47329 | L48: 2026-Q2
A49: CB-1127 | B49: Starter | C49: 63277 | D49: 45992 | E49: 62 | F49: 2 | G49: 3 | H49: 53.7 | I49: Churned | J49: Price increase at renewal | L49: 2025-Q4
A50: CB-1128 | B50: Enterprise | C50: 486816 | D50: 45940 | E50: 72.9 | F50: 3 | G50: 1 | H50: 59.1 | I50: Renewed | K50: 503261 | L50: 2025-Q4
A51: CB-1130 | B51: Enterprise | C51: 496827 | D51: 46021 | E51: 44.6 | F51: 4 | G51: 6 | H51: 38.7 | I51: Renewed - Upsold | K51: 623876 | L51: 2025-Q4
A52: CB-1133 | B52: Growth | C52: 146960 | D52: 46176 | E52: 66 | F52: 8 | G52: 0 | H52: 46.9 | I52: Renewed - Upsold | K52: 161125 | L52: 2026-Q2
A53: CB-1135 | B53: Enterprise | C53: 476134 | D53: 45790 | E53: 52.9 | F53: 5 | G53: 2 | H53: 43.9 | I53: Renewed | K53: 499151 | L53: 2025-Q2
A54: CB-1139 | B54: Growth | C54: 220991 | D54: 45910 | E54: 86.1 | F54: 4 | G54: 7 | H54: 61 | I54: Renewed - Upsold | K54: 283471 | L54: 2025-Q3
A55: CB-1145 | B55: Growth | C55: 108000 | D55: 46112 | E55: 58.1 | F55: 6 | G55: 0 | H55: 46.1 | I55: Renewed | K55: 108857 | L55: 2026-Q1
A56: CB-1146 | B56: Growth | C56: 189864 | D56: 46164 | E56: 58.5 | F56: 2 | G56: 11 | H56: 47 | I56: Renewed | K56: 185147 | L56: 2026-Q2
A57: CB-1149 | B57: Starter | C57: 53692 | D57: 45786 | E57: 72.3 | F57: 4 | G57: 0 | H57: 57.6 | I57: Renewed | K57: 55367 | L57: 2025-Q2
A58: CB-1152 | B58: Enterprise | C58: 505740 | D58: 45987 | E58: 73.2 | F58: 7 | G58: 3 | H58: 50.9 | I58: Renewed | K58: 496704 | L58: 2025-Q4
A59: CB-1154 | B59: Growth | C59: 155167 | D59: 45947 | E59: 84.5 | F59: 3 | G59: 13 | H59: 58.3 | I59: Renewed | K59: 152770 | L59: 2025-Q4
A60: CB-1156 | B60: Starter | C60: 81234 | D60: 46124 | E60: 97.4 | F60: 1 | G60: 4 | H60: 74.4 | I60: At Risk - Pending Decision | L60: 2026-Q2
A61: CB-1160 | B61: Starter | C61: 55452 | D61: 45946 | E61: 49.5 | F61: 4 | G61: 0 | H61: 45 | I61: Renewed | K61: 57164 | L61: 2025-Q4
A62: CB-1162 | B62: Starter | C62: 37917 | D62: 46080 | E62: 83.8 | F62: 3 | G62: 5 | H62: 62.7 | I62: Churned | J62: Champion left the company | L62: 2026-Q1
A63: CB-1163 | B63: Starter | C63: 54117 | D63: 45827 | E63: 57.3 | F63: 1 | G63: 0 | H63: 54.7 | I63: Renewed | K63: 56621 | L63: 2025-Q2
A64: CB-1165 | B64: Starter | C64: 50984 | D64: 46194 | E64: 55.7 | F64: 6 | G64: 3 | H64: 43 | I64: Renewed | K64: 52132 | L64: 2026-Q2
A65: CB-1168 | B65: Starter | C65: 69601 | D65: 46153 | E65: 84.5 | F65: 3 | G65: 1 | H65: 65.5 | I65: Renewed | K65: 70042 | L65: 2026-Q2
A66: CB-1170 | B66: Starter | C66: 54875 | D66: 46132 | E66: 84 | F66: 2 | G66: 5 | H66: 64.6 | I66: Churned | J66: Budget cuts | L66: 2026-Q2
A67: CB-1174 | B67: Starter | C67: 86696 | D67: 46014 | E67: 63.9 | F67: 0 | G67: 5 | H67: 57.2 | I67: At Risk - Pending Decision | L67: 2025-Q4
A68: CB-1175 | B68: Starter | C68: 62244 | D68: 45843 | E68: 74 | F68: 3 | G68: 2 | H68: 59.1 | I68: At Risk - Pending Decision | L68: 2025-Q3
A69: CB-1183 | B69: Growth | C69: 164888 | D69: 46152 | E69: 38.8 | F69: 3 | G69: 13 | H69: 33.2 | I69: Renewed - Upsold | K69: 192849 | L69: 2026-Q2
A70: CB-1186 | B70: Starter | C70: 61664 | D70: 46196 | E70: 70.9 | F70: 2 | G70: 5 | H70: 57.4 | I70: Churned | J70: Poor onboarding experience | L70: 2026-Q2
A71: CB-1187 | B71: Enterprise | C71: 485008 | D71: 45928 | E71: 74.5 | F71: 3 | G71: 0 | H71: 60.6 | I71: Renewed | K71: 498036 | L71: 2025-Q3
A72: CB-1189 | B72: Enterprise | C72: 563048 | D72: 46108 | E72: 62.2 | F72: 3 | G72: 0 | H72: 53.8 | I72: Renewed | K72: 568296 | L72: 2026-Q1
A73: CB-1194 | B73: Enterprise | C73: 624133 | D73: 46002 | E73: 46.6 | F73: 1 | G73: 9 | H73: 43.5 | I73: Renewed - Upsold | K73: 706929 | L73: 2025-Q4
A74: CB-1198 | B74: Enterprise | C74: 545774 | D74: 46047 | E74: 57.2 | F74: 5 | G74: 0 | H74: 47.4 | I74: At Risk - Pending Decision | L74: 2026-Q1
A75: CB-1199 | B75: Enterprise | C75: 675312 | D75: 46148 | E75: 58.8 | F75: 4 | G75: 0 | H75: 50.1 | I75: Renewed - Upsold | K75: 857202 | L75: 2026-Q2
A76: CB-1203 | B76: Enterprise | C76: 632726 | D76: 45991 | E76: 70.6 | F76: 4 | G76: 1 | H76: 56.1 | I76: Renewed | K76: 652210 | L76: 2025-Q4
A77: CB-1204 | B77: Starter | C77: 88855 | D77: 45761 | E77: 93.3 | F77: 3 | G77: 9 | H77: 65.5 | I77: Renewed | K77: 89874 | L77: 2025-Q2
A78: CB-1205 | B78: Enterprise | C78: 463270 | D78: 46079 | E78: 41.5 | F78: 3 | G78: 3 | H78: 40.6 | I78: Renewed | K78: 483438 | L78: 2026-Q1
A79: CB-1206 | B79: Starter | C79: 40978 | D79: 45977 | E79: 61 | F79: 2 | G79: 1 | H79: 54.3 | I79: Churned | J79: Low product adoption / usage | L79: 2025-Q4
A80: CB-1208 | B80: Starter | C80: 66101 | D80: 45964 | E80: 82.4 | F80: 2 | G80: 8 | H80: 61.9 | I80: Renewed | K80: 64345 | L80: 2025-Q4
A81: CB-1212 | B81: Growth | C81: 182795 | D81: 46051 | E81: 50.4 | F81: 2 | G81: 6 | H81: 45.5 | I81: Renewed - Upsold | K81: 244381 | L81: 2026-Q1
A82: CB-1216 | B82: Starter | C82: 71026 | D82: 45976 | E82: 68 | F82: 8 | G82: 0 | H82: 48 | I82: Renewed | K82: 69978 | L82: 2025-Q4
A83: CB-1217 | B83: Starter | C83: 73049 | D83: 45967 | E83: 72.5 | F83: 2 | G83: 0 | H83: 61.3 | I83: Renewed | K83: 73730 | L83: 2025-Q4
A84: CB-1220 | B84: Enterprise | C84: 610943 | D84: 46140 | E84: 71 | F84: 4 | G84: 14 | H84: 48.5 | I84: Renewed | K84: 595639 | L84: 2026-Q2
A85: CB-1224 | B85: Enterprise | C85: 465583 | D85: 46129 | E85: 51 | F85: 6 | G85: 0 | H85: 42.3 | I85: Renewed - Upsold | K85: 541953 | L85: 2026-Q2
A86: CB-1226 | B86: Starter | C86: 56000 | D86: 45796 | E86: 75.1 | F86: 6 | G86: 1 | H86: 54.9 | I86: Renewed | K86: 54437 | L86: 2025-Q2
A87: CB-1229 | B87: Starter | C87: 64268 | D87: 45944 | E87: 59 | F87: 4 | G87: 2 | H87: 49.1 | I87: Renewed | K87: 62872 | L87: 2025-Q4
A88: CB-1230 | B88: Enterprise | C88: 341115 | D88: 45987 | E88: 63.7 | F88: 5 | G88: 0 | H88: 51.1 | I88: Renewed | K88: 340605 | L88: 2025-Q4
A89: CB-1238 | B89: Starter | C89: 55614 | D89: 45774 | E89: 67.2 | F89: 4 | G89: 2 | H89: 53.6 | I89: Renewed | K89: 57033 | L89: 2025-Q2
A90: CB-1242 | B90: Growth | C90: 184910 | D90: 46082 | E90: 68.1 | F90: 3 | G90: 0 | H90: 57.1 | I90: Renewed | K90: 192904 | L90: 2026-Q1
A91: CB-1248 | B91: Growth | C91: 184478 | D91: 46196 | E91: 83.7 | F91: 7 | G91: 14 | H91: 50.1 | I91: Renewed | K91: 189255 | L91: 2026-Q2
... A93: CB-1254 | B93: Starter | C93: 57334 | D93: 46086 | E93: 73.8 | F93: 7 | G93: 11 | H93: 46.4 | I93: Renewed | K93: 56988 | L93: 2026-Q1
A94: CB-1257 | B94: Starter | C94: 44143 | D94: 45943 | E94: 56.5 | F94: 2 | G94: 1 | H94: 51.8 | I94: Churned | J94: Poor onboarding experience | L94: 2025-Q4
A95: CB-1258 | B95: Growth | C95: 193618 | D95: 45884 | E95: 69.2 | F95: 2 | G95: 1 | H95: 58.9 | I95: At Risk - Pending Decision | L95: 2025-Q3

Sheet Trend_Summary
A1: Quarter | B1: Avg Days to Onboard | C1: SLA Met % (<=14 days) | D1: Avg Onboarding CSAT | E1: Renewals Closed | F1: Renewed Count | G1: Renewal Rate % | H1: Churned Count | I1: Avg Health Score - Churned | J1: Avg Health Score - Renewed
A2: 2024-Q1 | B2: =IFERROR(ROUND(AVERAGEIFS(Clients_Onboarding!L:L,Clients_Onboarding!P:P,A2,Clients_Onboarding!M:M,"Completed"),1),"-") -> 10 | C2: =IFERROR(ROUND(COUNTIFS(Clients_Onboarding!P:P,A2,Clients_Onboarding!N:N,"Yes")/COUNTIFS(Clients_Onboarding!P:P,A2,Clients_Onboarding!M:M,"Completed"),3),"-") -> 1 | D2: =IFERROR(ROUND(AVERAGEIFS(Clients_Onboarding!O:O,Clients_Onboarding!P:P,A2),2),"-") -> 4.4 | E2: =COUNTIFS(Renewals_HealthScore!L:L,A2) -> 0 | F2: =COUNTIFS(Renewals_HealthScore!L:L,A2,Renewals_HealthScore!I:I,"Renewed")+COUNTIFS(Renewals_HealthScore!L:L,A2,Renewals_HealthScore!I:I,"Renewed - Upsold") -> 0 | G2: =IFERROR(ROUND(F2/E2,3),"-") -> - | H2: =COUNTIFS(Renewals_HealthScore!L:L,A2,Renewals_HealthScore!I:I,"Churned") -> 0 | I2: =IFERROR(ROUND(AVERAGEIFS(Renewals_HealthScore!H:H,Renewals_HealthScore!L:L,A2,Renewals_HealthScore!I:I,"Churned"),1),"-") -> - | J2: =IFERROR(ROUND(AVERAGEIFS(Renewals_HealthScore!H:H,Renewals_HealthScore!L:L,A2,Renewals_HealthScore!I:I,"Renewed"),1),"-") -> -
A3: 2024-Q2 | B3: =IFERROR(ROUND(AVERAGEIFS(Clients_Onboarding!L:L,Clients_Onboarding!P:P,A3,Clients_Onboarding!M:M,"Completed"),1),"-") -> 12.8 | C3: =IFERROR(ROUND(COUNTIFS(Clients_Onboarding!P:P,A3,Clients_Onboarding!N:N,"Yes")/COUNTIFS(Clients_Onboarding!P:P,A3,Clients_Onboarding!M:M,"Completed"),3),"-") -> 0.778 | D3: =IFERROR(ROUND(AVERAGEIFS(Clients_Onboarding!O:O,Clients_Onboarding!P:P,A3),2),"-") -> 3.92 | E3: =COUNTIFS(Renewals_HealthScore!L:L,A3) -> 0 | F3: =COUNTIFS(Renewals_HealthScore!L:L,A3,Renewals_HealthScore!I:I,"Renewed")+COUNTIFS(Renewals_HealthScore!L:L,A3,Renewals_HealthScore!I:I,"Renewed - Upsold") -> 0 | G3: =IFERROR(ROUND(F3/E3,3),"-") -> - | H3: =COUNTIFS(Renewals_HealthScore!L:L,A3,Renewals_HealthScore!I:I,"Churned") -> 0 | I3: =IFERROR(ROUND(AVERAGEIFS(Renewals_HealthScore!H:H,Renewals_HealthScore!L:L,A3,Renewals_HealthScore!I:I,"Churned"),1),"-") -> - | J3: =IFERROR(ROUND(AVERAGEIFS(Renewals_HealthScore!H:H,Renewals_HealthScore!L:L,A3,Renewals_HealthScore!I:I,"Renewed"),1),"-") -> -
A4: 2024-Q3 | B4: =IFERROR(ROUND(AVERAGEIFS(Clients_Onboarding!L:L,Clients_Onboarding!P:P,A4,Clients_Onboarding!M:M,"Completed"),1),"-") -> 15 | C4: =IFERROR(ROUND(COUNTIFS(Clients_Onboarding!P:P,A4,Clients_Onboarding!N:N,"Yes")/COUNTIFS(Clients_Onboarding!P:P,A4,Clients_Onboarding!M:M,"Completed"),3),"-") -> 0.5 | D4: =IFERROR(ROUND(AVERAGEIFS(Clients_Onboarding!O:O,Clients_Onboarding!P:P,A4),2),"-") -> 3.88 | E4: =COUNTIFS(Renewals_HealthScore!L:L,A4) -> 0 | F4: =COUNTIFS(Renewals_HealthScore!L:L,A4,Renewals_HealthScore!I:I,"Renewed")+COUNTIFS(Renewals_HealthScore!L:L,A4,Renewals_HealthScore!I:I,"Renewed - Upsold") -> 0 | G4: =IFERROR(ROUND(F4/E4,3),"-") -> - | H4: =COUNTIFS(Renewals_HealthScore!L:L,A4,Renewals_HealthScore!I:I,"Churned") -> 0 | I4: =IFERROR(ROUND(AVERAGEIFS(Renewals_HealthScore!H:H,Renewals_HealthScore!L:L,A4,Renewals_HealthScore!I:I,"Churned"),1),"-") -> - | J4: =IFERROR(ROUND(AVERAGEIFS(Renewals_HealthScore!H:H,Renewals_HealthScore!L:L,A4,Renewals_HealthScore!I:I,"Renewed"),1),"-") -> -
A5: 2024-Q4 | B5: =IFERROR(ROUND(AVERAGEIFS(Clients_Onboarding!L:L,Clients_Onboarding!P:P,A5,Clients_Onboarding!M:M,"Completed"),1),"-") -> 17 | C5: =IFERROR(ROUND(COUNTIFS(Clients_Onboarding!P:P,A5,Clients_Onboarding!N:N,"Yes")/COUNTIFS(Clients_Onboarding!P:P,A5,Clients_Onboarding!M:M,"Completed"),3),"-") -> 0.231 | D5: =IFERROR(ROUND(AVERAGEIFS(Clients_Onboarding!O:O,Clients_Onboarding!P:P,A5),2),"-") -> 4.06 | E5: =COUNTIFS(Renewals_HealthScore!L:L,A5) -> 0 | F5: =COUNTIFS(Renewals_HealthScore!L:L,A5,Renewals_HealthScore!I:I,"Renewed")+COUNTIFS(Renewals_HealthScore!L:L,A5,Renewals_HealthScore!I:I,"Renewed - Upsold") -> 0 | G5: =IFERROR(ROUND(F5/E5,3),"-") -> - | H5: =COUNTIFS(Renewals_HealthScore!L:L,A5,Renewals_HealthScore!I:I,"Churned") -> 0 | I5: =IFERROR(ROUND(AVERAGEIFS(Renewals_HealthScore!H:H,Renewals_HealthScore!L:L,A5,Renewals_HealthScore!I:I,"Churned"),1),"-") -> - | J5: =IFERROR(ROUND(AVERAGEIFS(Renewals_HealthScore!H:H,Renewals_HealthScore!L:L,A5,Renewals_HealthScore!I:I,"Renewed"),1),"-") -> -
A6: 2025-Q1 | B6: =IFERROR(ROUND(AVERAGEIFS(Clients_Onboarding!L:L,Clients_Onboarding!P:P,A6,Clients_Onboarding!M:M,"Completed"),1),"-") -> 17.8 | C6: =IFERROR(ROUND(COUNTIFS(Clients_Onboarding!P:P,A6,Clients_Onboarding!N:N,"Yes")/COUNTIFS(Clients_Onboarding!P:P,A6,Clients_Onboarding!M:M,"Completed"),3),"-") -> 0.263 | D6: =IFERROR(ROUND(AVERAGEIFS(Clients_Onboarding!O:O,Clients_Onboarding!P:P,A6),2),"-") -> 3.81 | E6: =COUNTIFS(Renewals_HealthScore!L:L,A6) -> 1 | F6: =COUNTIFS(Renewals_HealthScore!L:L,A6,Renewals_HealthScore!I:I,"Renewed")+COUNTIFS(Renewals_HealthScore!L:L,A6,Renewals_HealthScore!I:I,"Renewed - Upsold") -> 1 | G6: =IFERROR(ROUND(F6/E6,3),"-") -> 1 | H6: =COUNTIFS(Renewals_HealthScore!L:L,A6,Renewals_HealthScore!I:I,"Churned") -> 0 | I6: =IFERROR(ROUND(AVERAGEIFS(Renewals_HealthScore!H:H,Renewals_HealthScore!L:L,A6,Renewals_HealthScore!I:I,"Churned"),1),"-") -> - | J6: =IFERROR(ROUND(AVERAGEIFS(Renewals_HealthScore!H:H,Renewals_HealthScore!L:L,A6,Renewals_HealthScore!I:I,"Renewed"),1),"-") -> 49.6
A7: 2025-Q2 | B7: =IFERROR(ROUND(AVERAGEIFS(Clients_Onboarding!L:L,Clients_Onboarding!P:P,A7,Clients_Onboarding!M:M,"Completed"),1),"-") -> 19 | C7: =IFERROR(ROUND(COUNTIFS(Clients_Onboarding!P:P,A7,Clients_Onboarding!N:N,"Yes")/COUNTIFS(Clients_Onboarding!P:P,A7,Clients_Onboarding!M:M,"Completed"),3),"-") -> 0.185 | D7: =IFERROR(ROUND(AVERAGEIFS(Clients_Onboarding!O:O,Clients_Onboarding!P:P,A7),2),"-") -> 3.95 | E7: =COUNTIFS(Renewals_HealthScore!L:L,A7) -> 9 | F7: =COUNTIFS(Renewals_HealthScore!L:L,A7,Renewals_HealthScore!I:I,"Renewed")+COUNTIFS(Renewals_HealthScore!L:L,A7,Renewals_HealthScore!I:I,"Renewed - Upsold") -> 9 | G7: =IFERROR(ROUND(F7/E7,3),"-") -> 1 | H7: =COUNTIFS(Renewals_HealthScore!L:L,A7,Renewals_HealthScore!I:I,"Churned") -> 0 | I7: =IFERROR(ROUND(AVERAGEIFS(Renewals_HealthScore!H:H,Renewals_HealthScore!L:L,A7,Renewals_HealthScore!I:I,"Churned"),1),"-") -> - | J7: =IFERROR(ROUND(AVERAGEIFS(Renewals_HealthScore!H:H,Renewals_HealthScore!L:L,A7,Renewals_HealthScore!I:I,"Renewed"),1),"-") -> 54.8
A8: 2025-Q3 | B8: =IFERROR(ROUND(AVERAGEIFS(Clients_Onboarding!L:L,Clients_Onboarding!P:P,A8,Clients_Onboarding!M:M,"Completed"),1),"-") -> 22.6 | C8: =IFERROR(ROUND(COUNTIFS(Clients_Onboarding!P:P,A8,Clients_Onboarding!N:N,"Yes")/COUNTIFS(Clients_Onboarding!P:P,A8,Clients_Onboarding!M:M,"Completed"),3),"-") -> 0.053 | D8: =IFERROR(ROUND(AVERAGEIFS(Clients_Onboarding!O:O,Clients_Onboarding!P:P,A8),2),"-") -> 4.02 | E8: =COUNTIFS(Renewals_HealthScore!L:L,A8) -> 12 | F8: =COUNTIFS(Renewals_HealthScore!L:L,A8,Renewals_HealthScore!I:I,"Renewed")+COUNTIFS(Renewals_HealthScore!L:L,A8,Renewals_HealthScore!I:I,"Renewed - Upsold") -> 10 | G8: =IFERROR(ROUND(F8/E8,3),"-") -> 0.833 | H8: =COUNTIFS(Renewals_HealthScore!L:L,A8,Renewals_HealthScore!I:I,"Churned") -> 0 | I8: =IFERROR(ROUND(AVERAGEIFS(Renewals_HealthScore!H:H,Renewals_HealthScore!L:L,A8,Renewals_HealthScore!I:I,"Churned"),1),"-") -> - | J8: =IFERROR(ROUND(AVERAGEIFS(Renewals_HealthScore!H:H,Renewals_HealthScore!L:L,A8,Renewals_HealthScore!I:I,"Renewed"),1),"-") -> 56.8
A9: 2025-Q4 | B9: =IFERROR(ROUND(AVERAGEIFS(Clients_Onboarding!L:L,Clients_Onboarding!P:P,A9,Clients_Onboarding!M:M,"Completed"),1),"-") -> 22.7 | C9: =IFERROR(ROUND(COUNTIFS(Clients_Onboarding!P:P,A9,Clients_Onboarding!N:N,"Yes")/COUNTIFS(Clients_Onboarding!P:P,A9,Clients_Onboarding!M:M,"Completed"),3),"-") -> 0.026 | D9: =IFERROR(ROUND(AVERAGEIFS(Clients_Onboarding!O:O,Clients_Onboarding!P:P,A9),2),"-") -> 3.86 | E9: =COUNTIFS(Renewals_HealthScore!L:L,A9) -> 26 | F9: =COUNTIFS(Renewals_HealthScore!L:L,A9,Renewals_HealthScore!I:I,"Renewed")+COUNTIFS(Renewals_HealthScore!L:L,A9,Renewals_HealthScore!I:I,"Renewed - Upsold") -> 21 | G9: =IFERROR(ROUND(F9/E9,3),"-") -> 0.808 | H9: =COUNTIFS(Renewals_HealthScore!L:L,A9,Renewals_HealthScore!I:I,"Churned") -> 4 | I9: =IFERROR(ROUND(AVERAGEIFS(Renewals_HealthScore!H:H,Renewals_HealthScore!L:L,A9,Renewals_HealthScore!I:I,"Churned"),1),"-") -> 52.2 | J9: =IFERROR(ROUND(AVERAGEIFS(Renewals_HealthScore!H:H,Renewals_HealthScore!L:L,A9,Renewals_HealthScore!I:I,"Renewed"),1),"-") -> 54
A10: 2026-Q1 | B10: =IFERROR(ROUND(AVERAGEIFS(Clients_Onboarding!L:L,Clients_Onboarding!P:P,A10,Clients_Onboarding!M:M,"Completed"),1),"-") -> 25.1 | C10: =IFERROR(ROUND(COUNTIFS(Clients_Onboarding!P:P,A10,Clients_Onboarding!N:N,"Yes")/COUNTIFS(Clients_Onboarding!P:P,A10,Clients_Onboarding!M:M,"Completed"),3),"-") -> 0 | D10: =IFERROR(ROUND(AVERAGEIFS(Clients_Onboarding!O:O,Clients_Onboarding!P:P,A10),2),"-") -> 3.81 | E10: =COUNTIFS(Renewals_HealthScore!L:L,A10) -> 19 | F10: =COUNTIFS(Renewals_HealthScore!L:L,A10,Renewals_HealthScore!I:I,"Renewed")+COUNTIFS(Renewals_HealthScore!L:L,A10,Renewals_HealthScore!I:I,"Renewed - Upsold") -> 14 | G10: =IFERROR(ROUND(F10/E10,3),"-") -> 0.737 | H10: =COUNTIFS(Renewals_HealthScore!L:L,A10,Renewals_HealthScore!I:I,"Churned") -> 4 | I10: =IFERROR(ROUND(AVERAGEIFS(Renewals_HealthScore!H:H,Renewals_HealthScore!L:L,A10,Renewals_HealthScore!I:I,"Churned"),1),"-") -> 58.6 | J10: =IFERROR(ROUND(AVERAGEIFS(Renewals_HealthScore!H:H,Renewals_HealthScore!L:L,A10,Renewals_HealthScore!I:I,"Renewed"),1),"-") -> 52
A11: 2026-Q2 | B11: =IFERROR(ROUND(AVERAGEIFS(Clients_Onboarding!L:L,Clients_Onboarding!P:P,A11,Clients_Onboarding!M:M,"Completed"),1),"-") -> 26.5 | C11: =IFERROR(ROUND(COUNTIFS(Clients_Onboarding!P:P,A11,Clients_Onboarding!N:N,"Yes")/COUNTIFS(Clients_Onboarding!P:P,A11,Clients_Onboarding!M:M,"Completed"),3),"-") -> 0 | D11: =IFERROR(ROUND(AVERAGEIFS(Clients_Onboarding!O:O,Clients_Onboarding!P:P,A11),2),"-") -> 3.62 | E11: =COUNTIFS(Renewals_HealthScore!L:L,A11) -> 27 | F11: =COUNTIFS(Renewals_HealthScore!L:L,A11,Renewals_HealthScore!I:I,"Renewed")+COUNTIFS(Renewals_HealthScore!L:L,A11,Renewals_HealthScore!I:I,"Renewed - Upsold") -> 20 | G11: =IFERROR(ROUND(F11/E11,3),"-") -> 0.741 | H11: =COUNTIFS(Renewals_HealthScore!L:L,A11,Renewals_HealthScore!I:I,"Churned") -> 4 | I11: =IFERROR(ROUND(AVERAGEIFS(Renewals_HealthScore!H:H,Renewals_HealthScore!L:L,A11,Renewals_HealthScore!I:I,"Churned"),1),"-") -> 53.4 | J11: =IFERROR(ROUND(AVERAGEIFS(Renewals_HealthScore!H:H,Renewals_HealthScore!L:L,A11,Renewals_HealthScore!I:I,"Renewed"),1),"-") -> 55.5

Sheet Data_Dictionary
A1: Sheet | B1: Column | C1: Description
A2: Clients_Onboarding | B2: client_id | C2: Unique client identifier
A3: Clients_Onboarding | B3: company_name | C3: Fictional client company name
A4: Clients_Onboarding | B4: industry | C4: Client's industry vertical
A5: Clients_Onboarding | B5: region | C5: City/region of the client (India)
A6: Clients_Onboarding | B6: company_size | C6: Employee headcount band
A7: Clients_Onboarding | B7: plan_type | C7: Subscription tier: Starter / Growth / Enterprise
A8: Clients_Onboarding | B8: sales_rep | C8: Sales rep who closed the deal
A9: Clients_Onboarding | B9: csm_assigned | C9: Customer Success Manager assigned for onboarding
A10: Clients_Onboarding | B10: contract_signed_date | C10: Date the client signed the contract
A11: Clients_Onboarding | B11: onboarding_start_date | C11: Date onboarding officially began
A12: Clients_Onboarding | B12: onboarding_complete_date | C12: Date onboarding was marked complete (blank if dropped/in progress)
... A29: Renewals_HealthScore | B29: renewal_quarter | C29: Quarter the renewal decision fell in
